blockchain/__init__.py
blockchain/__main__.py
blockchain/chain_interface.py
blockchain/covalenth.py
blockchain/covaleth_chains.py
blockchain/setup.py
working/__init__.py
working/__main__.py
working/bitclout.py
working/c2.py
working/chain_interface.py
working/covalenth.py
working/covaleth_chains.py
working/fantom.py
working/luna.py
working/mina.py
working/moonriver.py
working/near.py
working/near_figment.py
working/one.py
working/one_staking.py
working/polkadot.py
working/polygon.py
working/ronin.py
working/ronin_c.py
working/substrate.py
working/substrate_chains.py
working/terra.py
blockchain_COHEN_DA-0.1.1.dist-info/METADATA
blockchain_COHEN_DA-0.1.1.dist-info/WHEEL
blockchain_COHEN_DA-0.1.1.dist-info/top_level.txt
blockchain_COHEN_DA-0.1.1.dist-info/RECORD
