Metadata-Version: 2.1
Name: blockchain-COHEN-DA
Version: 0.1.1
Summary: Transaction parsing for blockchains
Author: COHEN DA
Author-email: DIS-ASSURANCE-CRYPTO@cohencpa.com
License: UNKNOWN
Platform: UNKNOWN
